setup.cfg
setup.py
qap/__init__.py
qap/anatomical_preproc.py
qap/bids_utils.py
qap/cli.py
qap/cloud_utils.py
qap/dvars.py
qap/functional_preproc.py
qap/qap_utils.py
qap/qap_workflows.py
qap/qap_workflows_utils.py
qap/script_utils.py
qap/spatial_qc.py
qap/temporal_qc.py
qap/test_bids_utils.py
qap/test_cli.py
qap/test_dvars.py
qap/test_functional_preproc.py
qap/test_plotting.py
qap/test_qap_sublist_generator.py
qap/test_qap_utils.py
qap/test_qap_workflows.py
qap/test_script_utils.py
qap/test_spatial_qc.py
qap/test_temporal_qc.py
qap/version.py
qap/workflow_template.py
qap.egg-info/PKG-INFO
qap.egg-info/SOURCES.txt
qap.egg-info/dependency_links.txt
qap.egg-info/not-zip-safe
qap.egg-info/requires.txt
qap.egg-info/top_level.txt
qap/test_data/3dallineate_warp_brain.aff12.1D
qap/test_data/3dallineate_warp_head.aff12.1D
qap/test_data/MNI152_T1_3mm.nii.gz
qap/test_data/MNI152_T1_3mm_brain.nii.gz
qap/test_data/afni_linear_registration_graph.dot
qap/test_data/afni_segmentation_graph.dot
qap/test_data/allineate_warped_brain.nii.gz
qap/test_data/allineate_warped_head.nii.gz
qap/test_data/anat_bg_mask.nii.gz
qap/test_data/anat_bg_mask_nonzero.nii.gz
qap/test_data/anat_brain.nii.gz
qap/test_data/anat_reorient.nii.gz
qap/test_data/anat_reorient_graph.dot
qap/test_data/anat_skullstrip_graph.dot
qap/test_data/anatomical_csf_mask.nii.gz
qap/test_data/anatomical_gm_mask.nii.gz
qap/test_data/anatomical_scan.nii.gz
qap/test_data/anatomical_spatial_graph.dot
qap/test_data/anatomical_wm_mask.nii.gz
qap/test_data/ar1_output.p
qap/test_data/coordinate_transformation.aff12.1D
qap/test_data/func_motion_correct.nii.gz
qap/test_data/func_motion_correct_graph.dot
qap/test_data/func_preproc_graph.dot
qap/test_data/func_reorient.nii.gz
qap/test_data/functional_brain_mask.nii.gz
qap/test_data/functional_brain_mask_graph.dot
qap/test_data/functional_scan.nii.gz
qap/test_data/functional_spatial_graph.dot
qap/test_data/functional_temporal_graph.dot
qap/test_data/invert_functional_brain_mask_graph.dot
qap/test_data/inverted_functional_brain_mask.nii.gz
qap/test_data/loaded_func.p
qap/test_data/meanFD.1D
qap/test_data/mean_functional.nii.gz
