Metadata-Version: 1.1
Name: qap
Version: 1.0.8a0
Summary: A collection of three quality assessment pipelines for anatomical MRI and functional MRI scans.
Home-page: https://github.com/preprocessed-connectomes-project/quality-assessment-protocol
Author: Cameron Craddock, Zarrar Shehzad, Steven Giavasis,Daniel Clark
Author-email: cameron.craddock@childmind.org
License: UNKNOWN
Download-URL: https://github.com/preprocessed-connectomes-project/quality-assessment-protocol/archive/v1.0.8.zip
Platform: UNKNOWN
Requires: INDI_Tools (>=0.0.6)
Requires: Pillow (>=3.2.0)
Requires: PyPDF2 (>=1.26.0)
Requires: PyYAML (>=3.11)
Requires: argparse (>=1.2.1)
Requires: boto3 (>=1.3.1)
Requires: botocore (>=1.4.22)
Requires: cycler (>=0.10.0)
Requires: decorator (>=4.0.9)
Requires: docutils (>=0.12)
Requires: future (>=0.15.2)
Requires: futures (>=3.0.5)
Requires: html5lib (>=1.0b8)
Requires: httplib2 (>=0.9.2)
Requires: jmespath (>=0.9.0)
Requires: matplotlib (>=1.5.1)
Requires: networkx (>=1.11)
Requires: nibabel (>=2.0.2)
Requires: nitime (>=0.6)
Requires: nipype (>=0.12.1)
Requires: nose (>=1.3.7)
Requires: numpy (>=1.11.0)
Requires: pandas (>=0.18.1)
Requires: prov (>=1.4.0)
Requires: pyparsing (>=2.1.4)
Requires: python_dateutil (>=2.5.3)
Requires: pytz (>=2016.4)
Requires: reportlab (>=3.3.0)
Requires: scipy (>=0.17.1)
Requires: seaborn (>=0.7.0)
Requires: simplejson (>=3.8.2)
Requires: six (>=1.10.0)
Requires: traits (>=4.5.0)
Requires: wsgiref (>=0.1.2)
Requires: xhtml2pdf (>=0.1a4)
Requires: configparser (>=3.5.0)
